utrees/__init__.py
utrees/baltobot.py
utrees/kdi_quantizer.py
utrees/unmasking_trees.py
utrees-0.3.0.dist-info/LICENSE
utrees-0.3.0.dist-info/METADATA
utrees-0.3.0.dist-info/WHEEL
utrees-0.3.0.dist-info/top_level.txt
utrees-0.3.0.dist-info/zip-safe
utrees-0.3.0.dist-info/RECORD
