Metadata-Version: 2.1
Name: utrees
Version: 0.3.0
Summary: Unmasking trees for tabular data generation and imputation
Home-page: http://github.com/calvinmccarter/unmasking-trees
Author: Calvin McCarter
Author-email: mccarter.calvin@gmail.com
Maintainer: Calvin McCarter
Maintainer-email: mccarter.calvin@gmail.com
Keywords: tabular,imputation,generation
Classifier: Development Status :: 3 - Alpha
Classifier: Intended Audience :: Science/Research
Classifier: Intended Audience :: Developers
Classifier: License :: OSI Approved
Classifier: Programming Language :: Python
Classifier: Topic :: Software Development
Classifier: Topic :: Scientific/Engineering
Classifier: Operating System :: Microsoft :: Windows
Classifier: Operating System :: POSIX
Classifier: Operating System :: Unix
Classifier: Operating System :: MacOS
Classifier: Programming Language :: Python :: 3.6
Classifier: Programming Language :: Python :: 3.7
Classifier: Programming Language :: Python :: 3.8
Classifier: Programming Language :: Python :: 3.9
License-File: LICENSE
Requires-Dist: kditransform
Requires-Dist: numba >=0.48
Requires-Dist: numpy
Requires-Dist: pandas
Requires-Dist: scikit-learn >=0.23
Requires-Dist: scipy >=1.0
Requires-Dist: tqdm
Requires-Dist: xgboost
